<?xml version="1.0" encoding="UTF-8"?>
<FileConfig>
	<serverNode id="TempStoreNode">
		<ip>127.0.0.1</ip><!--节点存储位置(本地/远程服务器) 127.0.0.1 -->
		<port>21</port><!--ftp端口 -->
		<serverPort>9996</serverPort><!--该服务器上的文件系统端口 -->
		<userName>1709</userName><!-- 该服务器的登录用户名 -->
		<password>naruto</password><!-- 该服务器的登录密码 -->
		<url>http://localhost:90/portal/static/FileBase</url><!--该服务器的http访问路径-->
		<directoryNode id="TempFileStoreNode" storePath="D:/EclipseProject/deploy/webapps/portal/static/FileBase"><!--该服务器的存储根路径 -->
			<directoryNode id="temp" nameType="static" name="temp"><!--缓存文件夹 -->
				<redundancy switch="on"><!--是否进行文件删冗  on | off-->
					<fingerGenType type="server"><!--指纹产生方式 -->
						<property>fingerPrint</property><!--指纹映射属性名 -->
					</fingerGenType>
				</redundancy>
				<whiteList><!--该节点可以接收文件的白名单 -->
					JPG,JPEG,GIF,PNG,FLV,AVI,MOV,MPG,MP4,WMV,DOC,DOCX,PDF,XML,TXT,ZIP,RAR,XLS,XLSX
				</whiteList>
			</directoryNode>
		</directoryNode>
	</serverNode>
</FileConfig>